{
	"name": "AstixLeapCubeProcessing",
	"properties": {
		"activities": [
			{
				"name": "SpGetCubeProcessStatus",
				"type": "Lookup",
				"dependsOn": [],
				"policy": {
					"timeout": "0.12:00:00",
					"retry": 0,
					"retryIntervalInSeconds": 30,
					"secureOutput": false,
					"secureInput": false
				},
				"userProperties": [],
				"typeProperties": {
					"source": {
						"type": "SqlDWSource",
						"sqlReaderStoredProcedureName": "[dbo].[SpGetCubeProcessStatus]",
						"queryTimeout": "02:00:00",
						"partitionOption": "None"
					},
					"dataset": {
						"referenceName": "DataFoundationConnectionV2",
						"type": "DatasetReference"
					}
				}
			},
			{
				"name": "If Condition1",
				"type": "IfCondition",
				"dependsOn": [
					{
						"activity": "SpGetCubeProcessStatus",
						"dependencyConditions": [
							"Succeeded"
						]
					}
				],
				"userProperties": [],
				"typeProperties": {
					"expression": {
						"value": "@equals(int(activity('SpGetCubeProcessStatus').output.firstRow.cubereadytoprocess),1)",
						"type": "Expression"
					},
					"ifTrueActivities": [
						{
							"name": "AS_CubeProcess_PCode_Sync_Fact",
							"type": "ExecutePipeline",
							"dependsOn": [
								{
									"activity": "AS_ResumeandScale_S8",
									"dependencyConditions": [
										"Succeeded"
									]
								}
							],
							"userProperties": [],
							"typeProperties": {
								"pipeline": {
									"referenceName": "AS_CubeProcess_Pcode_Sync_Fact_V2",
									"type": "PipelineReference"
								},
								"waitOnCompletion": true,
								"parameters": {
									"flgcalled": 1,
									"TypeID": 1,
									"processdate": {
										"value": "@utcnow()",
										"type": "Expression"
									}
								}
							}
						},
						{
							"name": "SpGetCubeProcessStatusUpd_End",
							"type": "SqlServerStoredProcedure",
							"dependsOn": [
								{
									"activity": "AS_ResumeandScale_S4",
									"dependencyConditions": [
										"Succeeded"
									]
								}
							],
							"policy": {
								"timeout": "0.12:00:00",
								"retry": 0,
								"retryIntervalInSeconds": 30,
								"secureOutput": false,
								"secureInput": false
							},
							"userProperties": [],
							"typeProperties": {
								"storedProcedureName": "[dbo].[SpGetCubeProcessStatusUpd]",
								"storedProcedureParameters": {
									"flgEnd": {
										"value": "1",
										"type": "Byte"
									},
									"flgStart": {
										"value": "1",
										"type": "Byte"
									}
								}
							},
							"linkedServiceName": {
								"referenceName": "Dev_DataFoundationDB",
								"type": "LinkedServiceReference"
							}
						},
						{
							"name": "SpGetCubeProcessStatusUpd_Start",
							"type": "SqlServerStoredProcedure",
							"dependsOn": [],
							"policy": {
								"timeout": "0.12:00:00",
								"retry": 0,
								"retryIntervalInSeconds": 30,
								"secureOutput": false,
								"secureInput": false
							},
							"userProperties": [],
							"typeProperties": {
								"storedProcedureName": "[dbo].[SpGetCubeProcessStatusUpd]",
								"storedProcedureParameters": {
									"flgEnd": {
										"value": "0",
										"type": "Byte"
									},
									"flgStart": {
										"value": "1",
										"type": "Byte"
									}
								}
							},
							"linkedServiceName": {
								"referenceName": "Dev_DataFoundationDB",
								"type": "LinkedServiceReference"
							}
						},
						{
							"name": "AS_ResumeandScale_S8",
							"type": "ExecutePipeline",
							"dependsOn": [
								{
									"activity": "SpGetCubeProcessStatusUpd_Start",
									"dependencyConditions": [
										"Succeeded"
									]
								}
							],
							"userProperties": [],
							"typeProperties": {
								"pipeline": {
									"referenceName": "AS_ResumeandScale_S8",
									"type": "PipelineReference"
								},
								"waitOnCompletion": true
							}
						},
						{
							"name": "AS_ResumeandScale_S4",
							"type": "ExecutePipeline",
							"dependsOn": [
								{
									"activity": "AS_CubeProcess_PCode_Sync_Fact",
									"dependencyConditions": [
										"Succeeded"
									]
								}
							],
							"userProperties": [],
							"typeProperties": {
								"pipeline": {
									"referenceName": "AS_ResumeandScale_S4",
									"type": "PipelineReference"
								},
								"waitOnCompletion": true
							}
						},
						{
							"name": "Send Notification",
							"type": "ExecutePipeline",
							"dependsOn": [
								{
									"activity": "SpGetCubeProcessStatusUpd_End",
									"dependencyConditions": [
										"Succeeded"
									]
								}
							],
							"userProperties": [],
							"typeProperties": {
								"pipeline": {
									"referenceName": "Send Notification",
									"type": "PipelineReference"
								},
								"waitOnCompletion": true,
								"parameters": {
									"EmailTo": "Avinash@Astix.in,Alok@astix.in,Gaurav@astix.in,Varun@astix.in,Anuj@astix.in,rtdxhelpdesk@Astix.in",
									"Subject": "Astix Cube Process Successfully",
									"ErrorMessage": "Astix Cube Process Successfully"
								}
							}
						}
					]
				}
			}
		],
		"folder": {
			"name": "V2 Pipelines"
		},
		"annotations": []
	}
}