{
	"name": "LeapDataFullProcessDaily_Step1",
	"properties": {
		"activities": [
			{
				"name": "Loading Temp and Final Tables_Step1",
				"type": "ExecutePipeline",
				"dependsOn": [
					{
						"activity": "DW_Resume_Scale_V2",
						"dependencyConditions": [
							"Succeeded"
						]
					}
				],
				"userProperties": [],
				"typeProperties": {
					"pipeline": {
						"referenceName": "MiddleDFProcessing_Step1",
						"type": "PipelineReference"
					},
					"waitOnCompletion": true,
					"parameters": {
						"DataProcessDate": {
							"value": "@pipeline().parameters.DataProcessDate",
							"type": "Expression"
						}
					}
				}
			},
			{
				"name": "Wait1",
				"type": "Wait",
				"dependsOn": [],
				"userProperties": [],
				"typeProperties": {
					"waitTimeInSeconds": 1
				}
			},
			{
				"name": "DW_Resume_Scale_V2",
				"type": "ExecutePipeline",
				"dependsOn": [
					{
						"activity": "Wait1",
						"dependencyConditions": [
							"Succeeded"
						]
					}
				],
				"userProperties": [],
				"typeProperties": {
					"pipeline": {
						"referenceName": "DW_Resume_Scale_V2",
						"type": "PipelineReference"
					},
					"waitOnCompletion": true,
					"parameters": {
						"ScaleVal": "DW300c",
						"flgcalled": 1
					}
				}
			}
		],
		"parameters": {
			"DataProcessDate": {
				"type": "string"
			},
			"Container": {
				"type": "string"
			},
			"Directory": {
				"type": "string"
			}
		},
		"folder": {
			"name": "V2 Pipelines"
		},
		"annotations": [],
		"lastPublishTime": "2020-12-13T19:05:55Z"
	},
	"type": "Microsoft.DataFactory/factories/pipelines"
}